semantic_diff/__init__.py
semantic_diff/cli.py
semantic_diff/models.py
semantic_diff/analyzers/__init__.py
semantic_diff/analyzers/llm_analyzer.py
semantic_diff/formatters/__init__.py
semantic_diff/formatters/console_formatter.py
semantic_diff/parsers/__init__.py
semantic_diff/parsers/git_parser.py
semantic_diff-0.1.0.dist-info/METADATA
semantic_diff-0.1.0.dist-info/WHEEL
semantic_diff-0.1.0.dist-info/entry_points.txt
semantic_diff-0.1.0.dist-info/top_level.txt
semantic_diff-0.1.0.dist-info/RECORD
